{
    "products": [
      {
        "id": "1",
        "name": "Café americano",
        "price": 5,
        "type": "desayuno",
        "imagen": "https://raw.githubusercontent.com/rossvel-hub/CDMX011-burger-queen-api-client/SendOrders/src/assets/cafe1.jpg"
      },
      {
        "id": "2",
        "name": "Jugo de naranja",
        "price": 7,
        "type": "desayuno",
        "imagen": "https://raw.githubusercontent.com/rossvel-hub/CDMX011-burger-queen-api-client/SendOrders/src/assets/jugo.jpg"
      },
      {
        "id": "3",
        "name": "Café con leche",
        "price": 10,
        "type": "desayuno",
        "imagen": "https://raw.githubusercontent.com/rossvel-hub/CDMX011-burger-queen-api-client/SendOrders/src/assets/cafe2.jpg"
      },
      {
        "id": "4",
        "name": "Sandwich de J/Q",
        "price": 7,
        "type": "desayuno",
        "imagen": "https://raw.githubusercontent.com/rossvel-hub/CDMX011-burger-queen-api-client/SendOrders/src/assets/sandwich.jpg"
      },
      {
        "id": "5",
        "name": "Hamburguesa S",
        "price": 10,
        "type": "almuerzo",
        "imagen": "https://raw.githubusercontent.com/rossvel-hub/CDMX011-burger-queen-api-client/SendOrders/src/assets/ham.png"
      },
      {
        "id": "6",
        "name": "Hamburguesa D",
        "price": 15,
        "type": "almuerzo",
        "imagen": "https://raw.githubusercontent.com/rossvel-hub/CDMX011-burger-queen-api-client/SendOrders/src/assets/ham.png"
      },
      {
        "id": "7",
        "name": "Papas fritas",
        "price": 5,
        "type": "almuerzo",
        "imagen": "https://raw.githubusercontent.com/rossvel-hub/CDMX011-burger-queen-api-client/SendOrders/src/assets/papas.jpg"
      },
      {
        "id": "8",
        "name": "Aros de cebolla",
        "price": 5,
        "type": "almuerzo",
        "imagen": "https://raw.githubusercontent.com/rossvel-hub/CDMX011-burger-queen-api-client/SendOrders/src/assets/aros.jpg"
      },
      {
        "id": "9",
        "name": "Agua 500ml",
        "price": 5,
        "type": "almuerzo",
        "imagen": "https://raw.githubusercontent.com/rossvel-hub/CDMX011-burger-queen-api-client/SendOrders/src/assets/agua.jpg"
      },
      {
        "id": "10",
        "name": "Agua 750ml",
        "price": 7,
        "type": "almuerzo",
        "imagen": "https://raw.githubusercontent.com/rossvel-hub/CDMX011-burger-queen-api-client/SendOrders/src/assets/agua.jpg"
      },
      {
        "id": "11",
        "name": "Soda 500ml",
        "price": 7,
        "type": "almuerzo",
        "imagen": "https://raw.githubusercontent.com/rossvel-hub/CDMX011-burger-queen-api-client/SendOrders/src/assets/soda.jpg"
      },
      {
        "id": "12",
        "name": "Soda 750ml",
        "price": 10,
        "type": "almuerzo",
        "imagen": "https://raw.githubusercontent.com/rossvel-hub/CDMX011-burger-queen-api-client/SendOrders/src/assets/soda.jpg"
      }
    ],
    "Orders": [
      {
        "cliente": "",
        "estatus": "pediente",
        "productsToOrder": [
          {
            "id": "1",
            "name": "Café americano",
            "price": 5,
            "type": "desayuno",
            "qty": 1
          },
          {
            "id": "2",
            "name": "Jugo de naranja",
            "price": 7,
            "type": "desayuno",
            "qty": 1
          }
        ],
        "precioTotal": 12,
        "id": 1
      },
      {
        "cliente": "",
        "estatus": "pediente",
        "productsToOrder": [
          {
            "id": "1",
            "name": "Café americano",
            "price": 5,
            "type": "desayuno",
            "qty": 1
          },
          {
            "id": "2",
            "name": "Jugo de naranja",
            "price": 7,
            "type": "desayuno",
            "qty": 1
          }
        ],
        "precioTotal": 12,
        "id": 2
      },
      {
        "cliente": "",
        "estatus": "pediente",
        "productsToOrder": [
          {
            "id": "1",
            "name": "Café americano",
            "price": 5,
            "type": "desayuno",
            "qty": 1
          },
          {
            "id": "2",
            "name": "Jugo de naranja",
            "price": 7,
            "type": "desayuno",
            "qty": 1
          }
        ],
        "precioTotal": 12,
        "id": 3
      },
      {
        "cliente": "",
        "estatus": "pediente",
        "productsToOrder": [
          {
            "id": "1",
            "name": "Café americano",
            "price": 5,
            "type": "desayuno",
            "qty": 1
          },
          {
            "id": "2",
            "name": "Jugo de naranja",
            "price": 7,
            "type": "desayuno",
            "qty": 1
          },
          {
            "id": "3",
            "name": "Café con leche",
            "price": 10,
            "type": "desayuno",
            "qty": 1
          },
          {
            "id": "4",
            "name": "Sandwich de J/Q",
            "price": 7,
            "type": "desayuno",
            "qty": 1
          }
        ],
        "precioTotal": 29,
        "id": 4
      },
      {
        "cliente": "Jessi",
        "estatus": "pediente",
        "productsToOrder": [
          {
            "id": "1",
            "name": "Café americano",
            "price": 5,
            "type": "desayuno",
            "qty": 1
          },
          {
            "id": "2",
            "name": "Jugo de naranja",
            "price": 7,
            "type": "desayuno",
            "qty": 1
          }
        ],
        "precioTotal": 12,
        "id": 5
      },
      {
        "cliente": "Jessi",
        "estatus": "pediente",
        "productsToOrder": [
          {
            "id": "1",
            "name": "Café americano",
            "price": 5,
            "type": "desayuno",
            "qty": 1
          },
          {
            "id": "2",
            "name": "Jugo de naranja",
            "price": 7,
            "type": "desayuno",
            "qty": 1
          }
        ],
        "precioTotal": 12,
        "id": 6
      },
      {
        "cliente": "Almidon",
        "estatus": "pediente",
        "productsToOrder": [
          {
            "id": "8",
            "name": "Aros de cebolla",
            "price": 5,
            "type": "almuerzo",
            "qty": 1
          },
          {
            "id": "5",
            "name": "Hamburguesa S",
            "price": 10,
            "type": "almuerzo",
            "qty": 1
          },
          {
            "id": "11",
            "name": "Soda 500ml",
            "price": 7,
            "type": "almuerzo",
            "qty": 1
          }
        ],
        "precioTotal": 22,
        "id": 7
      },
      {
        "cliente": "Salome",
        "estatus": "pediente",
        "productsToOrder": [
          {
            "id": "1",
            "name": "Café americano",
            "price": 5,
            "type": "desayuno",
            "qty": 1
          },
          {
            "id": "5",
            "name": "Hamburguesa S",
            "price": 10,
            "type": "almuerzo",
            "qty": 1
          },
          {
            "id": "6",
            "name": "Hamburguesa D",
            "price": 15,
            "type": "almuerzo",
            "qty": 1
          }
        ],
        "precioTotal": 30,
        "id": 8
      },
      {
        "cliente": "",
        "estatus": "pediente",
        "productsToOrder": [
          {
            "id": "1",
            "name": "Café americano",
            "price": 5,
            "type": "desayuno",
            "qty": 1
          },
          {
            "id": "2",
            "name": "Jugo de naranja",
            "price": 7,
            "type": "desayuno",
            "qty": 1
          },
          {
            "id": "3",
            "name": "Café con leche",
            "price": 10,
            "type": "desayuno",
            "qty": 1
          },
          {
            "id": "4",
            "name": "Sandwich de J/Q",
            "price": 7,
            "type": "desayuno",
            "qty": 1
          }
        ],
        "precioTotal": 29,
        "id": 9
      },
      {
        "cliente": "Dani",
        "estatus": "pediente",
        "productsToOrder": [
          {
            "id": "1",
            "name": "Café americano",
            "price": 5,
            "type": "desayuno",
            "qty": 1
          },
          {
            "id": "2",
            "name": "Jugo de naranja",
            "price": 7,
            "type": "desayuno",
            "qty": 1
          },
          {
            "id": "3",
            "name": "Café con leche",
            "price": 10,
            "type": "desayuno",
            "qty": 1
          }
        ],
        "precioTotal": 22,
        "id": 13
      },
      {
        "cliente": "",
        "estatus": "pediente",
        "productsToOrder": [],
        "precioTotal": 0,
        "id": 14
      },
      {
        "cliente": "",
        "estatus": "pediente",
        "productsToOrder": [],
        "precioTotal": 0,
        "id": 15
      },
      {
        "cliente": "",
        "estatus": "pediente",
        "productsToOrder": [],
        "precioTotal": 0,
        "id": 16
      },
      {
        "cliente": "",
        "estatus": "pediente",
        "productsToOrder": [],
        "precioTotal": 0,
        "id": 17
      },
      {
        "cliente": "",
        "estatus": "pediente",
        "productsToOrder": [],
        "precioTotal": 0,
        "id": 18
      },
      {
        "cliente": "",
        "estatus": "pediente",
        "productsToOrder": [],
        "precioTotal": 0,
        "id": 19
      },
      {
        "cliente": "Ana",
        "estatus": "pediente",
        "productsToOrder": [
          {
            "id": "1",
            "name": "Café americano",
            "price": 5,
            "type": "desayuno",
            "qty": 1
          },
          {
            "id": "2",
            "name": "Jugo de naranja",
            "price": 7,
            "type": "desayuno",
            "qty": 1
          },
          {
            "id": "3",
            "name": "Café con leche",
            "price": 10,
            "type": "desayuno",
            "qty": 1
          }
        ],
        "precioTotal": 22,
        "id": 20
      },
      {
        "cliente": "",
        "estatus": "pediente",
        "productsToOrder": [
          {
            "id": "5",
            "name": "Hamburguesa S",
            "price": 10,
            "type": "almuerzo",
            "qty": 1
          },
          {
            "id": "6",
            "name": "Hamburguesa D",
            "price": 15,
            "type": "almuerzo",
            "qty": 1
          },
          {
            "id": "7",
            "name": "Papas fritas",
            "price": 5,
            "type": "almuerzo",
            "qty": 1
          },
          {
            "id": "8",
            "name": "Aros de cebolla",
            "price": 5,
            "type": "almuerzo",
            "qty": 1
          },
          {
            "id": "9",
            "name": "Agua 500ml",
            "price": 5,
            "type": "almuerzo",
            "qty": 1
          }
        ],
        "precioTotal": 40,
        "id": 21
      },
      {
        "cliente": "",
        "estatus": "pediente",
        "productsToOrder": [
          {
            "id": "5",
            "name": "Hamburguesa S",
            "price": 10,
            "type": "almuerzo",
            "imagen": "https://raw.githubusercontent.com/rossvel-hub/CDMX011-burger-queen-api-client/SendOrders/src/assets/ham.png",
            "qty": 1
          },
          {
            "id": "6",
            "name": "Hamburguesa D",
            "price": 15,
            "type": "almuerzo",
            "imagen": "https://raw.githubusercontent.com/rossvel-hub/CDMX011-burger-queen-api-client/SendOrders/src/assets/ham.png",
            "qty": 1
          },
          {
            "id": "7",
            "name": "Papas fritas",
            "price": 5,
            "type": "almuerzo",
            "imagen": "https://raw.githubusercontent.com/rossvel-hub/CDMX011-burger-queen-api-client/SendOrders/src/assets/papas.jpg",
            "qty": 1
          },
          {
            "id": "9",
            "name": "Agua 500ml",
            "price": 5,
            "type": "almuerzo",
            "imagen": "https://raw.githubusercontent.com/rossvel-hub/CDMX011-burger-queen-api-client/SendOrders/src/assets/agua.jpg",
            "qty": 1
          },
          {
            "id": "10",
            "name": "Agua 750ml",
            "price": 7,
            "type": "almuerzo",
            "imagen": "https://raw.githubusercontent.com/rossvel-hub/CDMX011-burger-queen-api-client/SendOrders/src/assets/agua.jpg",
            "qty": 1
          }
        ],
        "precioTotal": 42,
        "id": 22
      },
      {
        "cliente": "",
        "estatus": "pediente",
        "productsToOrder": [
          {
            "id": "9",
            "name": "Agua 500ml",
            "price": 5,
            "type": "almuerzo",
            "imagen": "https://raw.githubusercontent.com/rossvel-hub/CDMX011-burger-queen-api-client/SendOrders/src/assets/agua.jpg",
            "qty": 1
          },
          {
            "id": "10",
            "name": "Agua 750ml",
            "price": 7,
            "type": "almuerzo",
            "imagen": "https://raw.githubusercontent.com/rossvel-hub/CDMX011-burger-queen-api-client/SendOrders/src/assets/agua.jpg",
            "qty": 1
          }
        ],
        "precioTotal": 12,
        "id": 23
      },
      {
        "cliente": "",
        "estatus": "pediente",
        "productsToOrder": [
          {
            "id": "9",
            "name": "Agua 500ml",
            "price": 5,
            "type": "almuerzo",
            "imagen": "https://raw.githubusercontent.com/rossvel-hub/CDMX011-burger-queen-api-client/SendOrders/src/assets/agua.jpg",
            "qty": 1
          },
          {
            "id": "10",
            "name": "Agua 750ml",
            "price": 7,
            "type": "almuerzo",
            "imagen": "https://raw.githubusercontent.com/rossvel-hub/CDMX011-burger-queen-api-client/SendOrders/src/assets/agua.jpg",
            "qty": 1
          }
        ],
        "precioTotal": 12,
        "id": 24
      },
      {
        "cliente": "",
        "estatus": "pediente",
        "productsToOrder": [
          {
            "id": "9",
            "name": "Agua 500ml",
            "price": 5,
            "type": "almuerzo",
            "imagen": "https://raw.githubusercontent.com/rossvel-hub/CDMX011-burger-queen-api-client/SendOrders/src/assets/agua.jpg",
            "qty": 1
          },
          {
            "id": "10",
            "name": "Agua 750ml",
            "price": 7,
            "type": "almuerzo",
            "imagen": "https://raw.githubusercontent.com/rossvel-hub/CDMX011-burger-queen-api-client/SendOrders/src/assets/agua.jpg",
            "qty": 1
          }
        ],
        "precioTotal": 12,
        "id": 25
      },
      {
        "cliente": "",
        "estatus": "pediente",
        "productsToOrder": [
          {
            "id": "9",
            "name": "Agua 500ml",
            "price": 5,
            "type": "almuerzo",
            "imagen": "https://raw.githubusercontent.com/rossvel-hub/CDMX011-burger-queen-api-client/SendOrders/src/assets/agua.jpg",
            "qty": 1
          },
          {
            "id": "10",
            "name": "Agua 750ml",
            "price": 7,
            "type": "almuerzo",
            "imagen": "https://raw.githubusercontent.com/rossvel-hub/CDMX011-burger-queen-api-client/SendOrders/src/assets/agua.jpg",
            "qty": 1
          }
        ],
        "precioTotal": 12,
        "id": 26
      },
      {
        "cliente": "Alice",
        "estatus": "pediente",
        "productsToOrder": [
          {
            "id": "5",
            "name": "Hamburguesa S",
            "price": 10,
            "type": "almuerzo",
            "imagen": "https://raw.githubusercontent.com/rossvel-hub/CDMX011-burger-queen-api-client/SendOrders/src/assets/ham.png",
            "qty": 1
          },
          {
            "id": "6",
            "name": "Hamburguesa D",
            "price": 15,
            "type": "almuerzo",
            "imagen": "https://raw.githubusercontent.com/rossvel-hub/CDMX011-burger-queen-api-client/SendOrders/src/assets/ham.png",
            "qty": 1
          },
          {
            "id": "7",
            "name": "Papas fritas",
            "price": 5,
            "type": "almuerzo",
            "imagen": "https://raw.githubusercontent.com/rossvel-hub/CDMX011-burger-queen-api-client/SendOrders/src/assets/papas.jpg",
            "qty": 1
          },
          {
            "id": "8",
            "name": "Aros de cebolla",
            "price": 5,
            "type": "almuerzo",
            "imagen": "https://raw.githubusercontent.com/rossvel-hub/CDMX011-burger-queen-api-client/SendOrders/src/assets/aros.jpg",
            "qty": 1
          },
          {
            "id": "9",
            "name": "Agua 500ml",
            "price": 5,
            "type": "almuerzo",
            "imagen": "https://raw.githubusercontent.com/rossvel-hub/CDMX011-burger-queen-api-client/SendOrders/src/assets/agua.jpg",
            "qty": 1
          },
          {
            "id": "10",
            "name": "Agua 750ml",
            "price": 7,
            "type": "almuerzo",
            "imagen": "https://raw.githubusercontent.com/rossvel-hub/CDMX011-burger-queen-api-client/SendOrders/src/assets/agua.jpg",
            "qty": 1
          },
          {
            "id": "11",
            "name": "Soda 500ml",
            "price": 7,
            "type": "almuerzo",
            "imagen": "https://raw.githubusercontent.com/rossvel-hub/CDMX011-burger-queen-api-client/SendOrders/src/assets/soda.jpg",
            "qty": 1
          },
          {
            "id": "12",
            "name": "Soda 750ml",
            "price": 10,
            "type": "almuerzo",
            "imagen": "https://raw.githubusercontent.com/rossvel-hub/CDMX011-burger-queen-api-client/SendOrders/src/assets/soda.jpg",
            "qty": 1
          }
        ],
        "precioTotal": 64,
        "id": 27
      },
      {
        "cliente": "Alice",
        "estatus": "pediente",
        "productsToOrder": [
          {
            "id": "5",
            "name": "Hamburguesa S",
            "price": 10,
            "type": "almuerzo",
            "imagen": "https://raw.githubusercontent.com/rossvel-hub/CDMX011-burger-queen-api-client/SendOrders/src/assets/ham.png",
            "qty": 1
          },
          {
            "id": "6",
            "name": "Hamburguesa D",
            "price": 15,
            "type": "almuerzo",
            "imagen": "https://raw.githubusercontent.com/rossvel-hub/CDMX011-burger-queen-api-client/SendOrders/src/assets/ham.png",
            "qty": 1
          },
          {
            "id": "7",
            "name": "Papas fritas",
            "price": 5,
            "type": "almuerzo",
            "imagen": "https://raw.githubusercontent.com/rossvel-hub/CDMX011-burger-queen-api-client/SendOrders/src/assets/papas.jpg",
            "qty": 1
          },
          {
            "id": "8",
            "name": "Aros de cebolla",
            "price": 5,
            "type": "almuerzo",
            "imagen": "https://raw.githubusercontent.com/rossvel-hub/CDMX011-burger-queen-api-client/SendOrders/src/assets/aros.jpg",
            "qty": 1
          },
          {
            "id": "9",
            "name": "Agua 500ml",
            "price": 5,
            "type": "almuerzo",
            "imagen": "https://raw.githubusercontent.com/rossvel-hub/CDMX011-burger-queen-api-client/SendOrders/src/assets/agua.jpg",
            "qty": 1
          },
          {
            "id": "10",
            "name": "Agua 750ml",
            "price": 7,
            "type": "almuerzo",
            "imagen": "https://raw.githubusercontent.com/rossvel-hub/CDMX011-burger-queen-api-client/SendOrders/src/assets/agua.jpg",
            "qty": 1
          },
          {
            "id": "11",
            "name": "Soda 500ml",
            "price": 7,
            "type": "almuerzo",
            "imagen": "https://raw.githubusercontent.com/rossvel-hub/CDMX011-burger-queen-api-client/SendOrders/src/assets/soda.jpg",
            "qty": 1
          },
          {
            "id": "12",
            "name": "Soda 750ml",
            "price": 10,
            "type": "almuerzo",
            "imagen": "https://raw.githubusercontent.com/rossvel-hub/CDMX011-burger-queen-api-client/SendOrders/src/assets/soda.jpg",
            "qty": 1
          }
        ],
        "precioTotal": 64,
        "id": 28
      },
      {
        "cliente": "ale",
        "estatus": "pediente",
        "productsToOrder": [
          {
            "id": "1",
            "name": "Café americano",
            "price": 5,
            "type": "desayuno",
            "imagen": "https://raw.githubusercontent.com/rossvel-hub/CDMX011-burger-queen-api-client/SendOrders/src/assets/cafe1.jpg",
            "qty": 1
          }
        ],
        "precioTotal": 5,
        "id": 29
      },
      {
        "cliente": "al",
        "estatus": "pediente",
        "productsToOrder": [
          {
            "id": "1",
            "name": "Café americano",
            "price": 5,
            "type": "desayuno",
            "imagen": "https://raw.githubusercontent.com/rossvel-hub/CDMX011-burger-queen-api-client/SendOrders/src/assets/cafe1.jpg",
            "qty": 1
          }
        ],
        "precioTotal": 5,
        "id": 30
      },
      {
        "cliente": "al",
        "estatus": "pediente",
        "productsToOrder": [
          {
            "id": "1",
            "name": "Café americano",
            "price": 5,
            "type": "desayuno",
            "imagen": "https://raw.githubusercontent.com/rossvel-hub/CDMX011-burger-queen-api-client/SendOrders/src/assets/cafe1.jpg",
            "qty": 1
          }
        ],
        "precioTotal": 5,
        "id": 31
      },
      {
        "cliente": "Eli",
        "estatus": "pediente",
        "productsToOrder": [
          {
            "id": "1",
            "name": "Café americano",
            "price": 5,
            "type": "desayuno",
            "imagen": "https://raw.githubusercontent.com/rossvel-hub/CDMX011-burger-queen-api-client/SendOrders/src/assets/cafe1.jpg",
            "qty": 1
          }
        ],
        "precioTotal": 5,
        "id": 32
      },
      {
        "cliente": "Eli",
        "estatus": "pediente",
        "productsToOrder": [
          {
            "id": "1",
            "name": "Café americano",
            "price": 5,
            "type": "desayuno",
            "imagen": "https://raw.githubusercontent.com/rossvel-hub/CDMX011-burger-queen-api-client/SendOrders/src/assets/cafe1.jpg",
            "qty": 1
          }
        ],
        "precioTotal": 5,
        "id": 33
      },
      {
        "cliente": "Alice",
        "estatus": "pediente",
        "productsToOrder": [
          {
            "id": "1",
            "name": "Café americano",
            "price": 5,
            "type": "desayuno",
            "imagen": "https://raw.githubusercontent.com/rossvel-hub/CDMX011-burger-queen-api-client/SendOrders/src/assets/cafe1.jpg",
            "qty": 1
          }
        ],
        "precioTotal": 5,
        "id": 34
      },
      {
        "cliente": "Kiko",
        "estatus": "pediente",
        "productsToOrder": [
          {
            "id": "1",
            "name": "Café americano",
            "price": 5,
            "type": "desayuno",
            "imagen": "https://raw.githubusercontent.com/rossvel-hub/CDMX011-burger-queen-api-client/SendOrders/src/assets/cafe1.jpg",
            "qty": 1
          }
        ],
        "precioTotal": 5,
        "id": 35
      },
      {
        "cliente": "Aliss",
        "estatus": "pediente",
        "productsToOrder": [
          {
            "id": "1",
            "name": "Café americano",
            "price": 5,
            "type": "desayuno",
            "imagen": "https://raw.githubusercontent.com/rossvel-hub/CDMX011-burger-queen-api-client/SendOrders/src/assets/cafe1.jpg",
            "qty": 1
          }
        ],
        "precioTotal": 5,
        "id": 36
      },
      {
        "cliente": "Jessi",
        "estatus": "pediente",
        "productsToOrder": [
          {
            "id": "1",
            "name": "Café americano",
            "price": 5,
            "type": "desayuno",
            "imagen": "https://raw.githubusercontent.com/rossvel-hub/CDMX011-burger-queen-api-client/SendOrders/src/assets/cafe1.jpg",
            "qty": 1
          }
        ],
        "precioTotal": 5,
        "id": 37
      },
      {
        "cliente": "Coco",
        "estatus": "pediente",
        "productsToOrder": [
          {
            "id": "1",
            "name": "Café americano",
            "price": 5,
            "type": "desayuno",
            "imagen": "https://raw.githubusercontent.com/rossvel-hub/CDMX011-burger-queen-api-client/SendOrders/src/assets/cafe1.jpg",
            "qty": 1
          }
        ],
        "precioTotal": 5,
        "id": 38
      },
      {
        "cliente": "ali",
        "estatus": "pediente",
        "productsToOrder": [
          {
            "id": "1",
            "name": "Café americano",
            "price": 5,
            "type": "desayuno",
            "imagen": "https://raw.githubusercontent.com/rossvel-hub/CDMX011-burger-queen-api-client/SendOrders/src/assets/cafe1.jpg",
            "qty": 1
          }
        ],
        "precioTotal": 5,
        "id": 39
      },
      {
        "cliente": "Ale",
        "estatus": "pediente",
        "productsToOrder": [
          {
            "id": "1",
            "name": "Café americano",
            "price": 5,
            "type": "desayuno",
            "imagen": "https://raw.githubusercontent.com/rossvel-hub/CDMX011-burger-queen-api-client/SendOrders/src/assets/cafe1.jpg",
            "qty": 1
          }
        ],
        "precioTotal": 5,
        "id": 40
      }
    ]
  }